{
  "generator-jhipster": {
    "applicationType": "microservice",
    "gitCompany": "",
    "baseName": "driverApp",
    "packageName": "com.driverapp",
    "packageFolder": "com/driverapp",
    "serverPort": 8081,
    "serviceDiscoveryType": false,
    "authenticationType": "jwt",
    "uaaBaseName": "../uaa",
    "cacheProvider": "no",
    "enableHibernateCache": false,
    "websocket": false,
    "databaseType": "mongodb",
    "devDatabaseType": "mongodb",
    "prodDatabaseType": "mongodb",
    "searchEngine": "elasticsearch",
    "enableSwaggerCodegen": false,
    "messageBroker": false,
    "buildTool": "maven",
    "useSass": false,
    "clientPackageManager": "npm",
    "testFrameworks": [],
    "enableTranslation": false,
    "nativeLanguage": "en",
    "languages": [
      "en"
    ],
    "clientFramework": "angularX",
    "jhiPrefix": "jhi",
    "jhipsterVersion": "6.0.1",
    "jwtSecretKey": "Yjg2YjJjNzJiYzQ1ZTZjMjE1NjdkZGQyMjcyNGVhMjJhODIyYTA5NjA5Njk2M2FkNjM2NzFmZWQ4Njk1OGI1NmFkODA0MzU1ZmE0OWI0ZTYyOThlYWI4MzJlYWE2NTE0NWQ3OTlhMzNmMzA5MzkwYjM3NTI3NjFjOTU4MTM5YWY=",
    "entitySuffix": "",
    "dtoSuffix": "DTO",
    "otherModules": [],
    "blueprints": [],
    "skipClient": true,
    "skipUserManagement": true
  },
  "git-provider": "GitHub",
  "git-company": "itachiunited",
  "repository-name": "driver-app"
}